README.rst
setup.py
simpleobserver.py
simpleobserver.egg-info/PKG-INFO
simpleobserver.egg-info/SOURCES.txt
simpleobserver.egg-info/dependency_links.txt
simpleobserver.egg-info/top_level.txt