Metadata-Version: 1.1
Name: simpleobserver
Version: 1.0.3
Summary: A very simple implementation of the observer pattern
Home-page: http://github.com/cooper-software/observer
Author: Elisha Fitch-Cook
Author-email: elisha@cooper.com
License: MIT
Keywords: events,patterns,observer
Platform: UNKNOWN
Classifier: Development Status :: 5 - Production/Stable
Classifier: Environment :: Console
Classifier: Environment :: MacOS X
Classifier: Environment :: Web Environment
Classifier: Environment :: Win32 (MS Windows)
Classifier: Environment :: X11 Applications
Classifier: Intended Audience :: Developers
Classifier: License :: OSI Approved :: MIT License
Classifier: Natural Language :: English
Classifier: Programming Language :: Python
Classifier: Programming Language :: Python :: 2.7
Classifier: Programming Language :: Python :: 3.4
